metals_api/__init__.py
metals_api/client.py
metals_api-0.4.dist-info/METADATA
metals_api-0.4.dist-info/WHEEL
metals_api-0.4.dist-info/top_level.txt
metals_api-0.4.dist-info/RECORD
