Metadata-Version: 2.1
Name: metals_api
Version: 0.4
Summary: A Python package to get the latest metals prices from the Metals-API
Home-page: https://github.com/Zyla-Labs/pypi-metals-api
Author: Metals-API
Author-email: support@metals-api.com
Keywords: metals-api,precious metals api,metals api,metals, precious metals,gold,silver,Platinum,Palladium,Ruthenium,Rhodium,forex data,rates,money,usd,eur,btc,forex api,gbp to usd,gbp to eur,eur to usd,api,currency api,exchange rate api,get currency rates api,currency rates php,usd to eur api,copper,nickel,aluminium,TIN,Zinc
